monquery/__init__.py
monquery/db.py
monquery/fltr.py
monquery/paginate.py
monquery/parse.py
monquery/sort.py
monquery/util.py
monquery-0.3.0.dist-info/LICENSE
monquery-0.3.0.dist-info/WHEEL
monquery-0.3.0.dist-info/METADATA
monquery-0.3.0.dist-info/RECORD
